[
    {
        "id": 0,
        "username": "root",
        "phoneNumber": "18179396328",
        "password": "202cb962ac59075b964b07152d234b70",
        "power": 0
    },
    {
        "id": 1,
        "phoneNumber": "13157829546",
        "username": "李华",
        "password": "202cb962ac59075b964b07152d234b70",
        "profile": "/img/profile/user_man.png",
        "power": 1,
        "createTime": "2023-05-26T00:00:00Z",
        "sex": 1,
        "age": 41
    },
    {
        "id": 2,
        "phoneNumber": "13915729846",
        "username": "周伟",
        "password": "202cb962ac59075b964b07152d234b70",
        "profile": "/img/profile/user_man.png",
        "power": 1,
        "createTime": "2023-05-26T00:00:00Z",
        "sex": 1,
        "age": 41
    },
    {
        "id": 3,
        "phoneNumber": "13789524618",
        "username": "张小磊",
        "password": "202cb962ac59075b964b07152d234b70",
        "profile": "/img/profile/user_man.png",
        "power": 2,
        "createTime": "2023-05-26T00:00:00Z",
        "sex": 1,
        "age": 36
    },
    {
        "id": 4,
        "phoneNumber": "13985246179",
        "username": "吴敏",
        "password": "202cb962ac59075b964b07152d234b70",
        "profile": "/img/profile/user_man.png",
        "power": 2,
        "createTime": "2023-05-26T00:00:00Z",
        "sex": 1,
        "age": 39
    },
    {
        "id": 5,
        "phoneNumber": "13579246813",
        "username": "王浩",
        "password": "202cb962ac59075b964b07152d234b70",
        "profile": "/img/profile/user_man.png",
        "power": 2,
        "createTime": "2023-05-26T00:00:00Z",
        "sex": 1,
        "age": 41
    },
    {
        "id": 6,
        "phoneNumber": "13467925812",
        "username": "赵静安",
        "password": "202cb962ac59075b964b07152d234b70",
        "profile": "/img/profile/user_woman.png",
        "power": 2,
        "createTime": "2023-05-26T00:00:00Z",
        "sex": 0,
        "age": 33
    },
    {
        "id": 7,
        "phoneNumber": "13679124538",
        "username": "陈明",
        "password": "202cb962ac59075b964b07152d234b70",
        "profile": "/img/profile/user_man.png",
        "power": 2,
        "createTime": "2023-05-26T00:00:00Z",
        "sex": 1,
        "age": 46
    },
    {
        "id": 8,
        "phoneNumber": "13874126953",
        "username": "刘泽安",
        "password": "202cb962ac59075b964b07152d234b70",
        "profile": "/img/profile/user_man.png",
        "power": 2,
        "createTime": "2023-05-26T00:00:00Z",
        "sex": 1,
        "age": 41
    },
    {
        "id": 9,
        "phoneNumber": "13975483162",
        "username": "杨秀",
        "password": "202cb962ac59075b964b07152d234b70",
        "profile": "/img/profile/user_man.png",
        "power": 2,
        "createTime": "2023-05-26T00:00:00Z",
        "sex": 1,
        "age": 46
    },
    {
        "id": 10,
        "phoneNumber": "13851249763",
        "username": "黄宇天",
        "password": "202cb962ac59075b964b07152d234b70",
        "profile": "/img/profile/user_man.png",
        "power": 2,
        "createTime": "2023-05-26T00:00:00Z",
        "sex": 1,
        "age": 34
    },
    {
        "id": 11,
        "phoneNumber": "13741926835",
        "username": "林横峰",
        "password": "202cb962ac59075b964b07152d234b70",
        "profile": "/img/profile/user_man.png",
        "power": 3,
        "createTime": "2023-05-26T00:00:00Z",
        "sex": 1,
        "age": 41
    },
    {
        "id": 12,
        "phoneNumber": "13589641732",
        "username": "何小雪",
        "password": "202cb962ac59075b964b07152d234b70",
        "profile": "/img/profile/user_woman.png",
        "power": 3,
        "createTime": "2023-05-26T00:00:00Z",
        "sex": 0,
        "age": 33
    },
    {
        "id": 13,
        "phoneNumber": "13915624837",
        "username": "胡晓",
        "password": "202cb962ac59075b964b07152d234b70",
        "profile": "/img/profile/user_woman.png",
        "power": 3,
        "createTime": "2023-05-26T00:00:00Z",
        "sex": 0,
        "age": 54
    },
    {
        "id": 14,
        "phoneNumber": "13951864237",
        "username": "朱强",
        "password": "202cb962ac59075b964b07152d234b70",
        "profile": "/img/profile/user_man.png",
        "power": 3,
        "createTime": "2023-05-26T00:00:00Z",
        "sex": 1,
        "age": 54
    },
    {
        "id": 15,
        "phoneNumber": "13924613587",
        "username": "罗丽",
        "password": "202cb962ac59075b964b07152d234b70",
        "profile": "/img/profile/user_woman.png",
        "power": 3,
        "createTime": "2023-05-26T00:00:00Z",
        "sex": 0,
        "age": 36
    },
    {
        "id": 16,
        "phoneNumber": "13965342817",
        "username": "叶娟",
        "password": "202cb962ac59075b964b07152d234b70",
        "profile": "/img/profile/user_woman.png",
        "power": 3,
        "createTime": "2023-05-26T00:00:00Z",
        "sex": 0,
        "age": 50
    },
    {
        "id": 17,
        "phoneNumber": "13857496321",
        "username": "韩勇",
        "password": "202cb962ac59075b964b07152d234b70",
        "profile": "/img/profile/user_man.png",
        "power": 4,
        "createTime": "2023-05-26T00:00:00Z",
        "sex": 1,
        "age": 25
    },
    {
        "id": 18,
        "phoneNumber": "13986421573",
        "username": "谢芳",
        "password": "202cb962ac59075b964b07152d234b70",
        "profile": "/img/profile/user_woman.png",
        "power": 4,
        "createTime": "2023-05-26T00:00:00Z",
        "sex": 0,
        "age": 25
    },
    {
        "id": 19,
        "phoneNumber": "13741692853",
        "username": "孔涛",
        "password": "202cb962ac59075b964b07152d234b70",
        "profile": "/img/profile/user_man.png",
        "power": 4,
        "createTime": "2023-05-26T00:00:00Z",
        "sex": 1,
        "age": 41
    },
    {
        "id": 20,
        "phoneNumber": "13916842597",
        "username": "曹艳",
        "password": "202cb962ac59075b964b07152d234b70",
        "profile": "/img/profile/user_woman.png",
        "power": 4,
        "createTime": "2023-05-26T00:00:00Z",
        "sex": 0,
        "age": 36
    },
    {
        "id": 21,
        "phoneNumber": "13895271364",
        "username": "傅霞",
        "password": "202cb962ac59075b964b07152d234b70",
        "profile": "/img/profile/user_woman.png",
        "power": 4,
        "createTime": "2023-05-26T00:00:00Z",
        "sex": 0,
        "age": 54
    },
    {
        "id": 22,
        "phoneNumber": "13874126953",
        "username": "毛辉光",
        "password": "202cb962ac59075b964b07152d234b70",
        "profile": "/img/profile/user_man.png",
        "power": 4,
        "createTime": "2023-05-26T00:00:00Z",
        "sex": 1,
        "age": 41
    },
    {
        "id": 23,
        "phoneNumber": "13915836247",
        "username": "秦丽",
        "password": "202cb962ac59075b964b07152d234b70",
        "profile": "/img/profile/user_woman.png",
        "power": 4,
        "createTime": "2023-05-26T00:00:00Z",
        "sex": 0,
        "age": 46
    },
    {
        "id": 24,
        "phoneNumber": "13974265831",
        "username": "程杰",
        "password": "202cb962ac59075b964b07152d234b70",
        "profile": "/img/profile/user_man.png",
        "power": 4,
        "createTime": "2023-05-26T00:00:00Z",
        "sex": 1,
        "age": 41
    },
    {
        "id": 25,
        "phoneNumber": "13987514263",
        "username": "邵婷",
        "password": "202cb962ac59075b964b07152d234b70",
        "profile": "/img/profile/user_woman.png",
        "power": 4,
        "createTime": "2023-05-26T00:00:00Z",
        "sex": 0,
        "age": 35
    },
    {
        "id": 26,
        "phoneNumber": "13851694273",
        "username": "宋辉",
        "password": "202cb962ac59075b964b07152d234b70",
        "profile": "/img/profile/user_man.png",
        "power": 4,
        "createTime": "2023-05-26T00:00:00Z",
        "sex": 1,
        "age": 36
    },
    {
        "id": 27,
        "phoneNumber": "13942851673",
        "username": "邱平",
        "password": "202cb962ac59075b964b07152d234b70",
        "profile": "/img/profile/user_man.png",
        "power": 4,
        "createTime": "2023-05-26T00:00:00Z",
        "sex": 1,
        "age": 41
    },
    {
        "id": 28,
        "phoneNumber": "13895612743",
        "username": "潘芬",
        "password": "202cb962ac59075b964b07152d234b70",
        "profile": "/img/profile/user_woman.png",
        "power": 4,
        "createTime": "2023-05-26T00:00:00Z",
        "sex": 0,
        "age": 41
    }
]
